Listing18_1.py
greetings_helloworld2030_2-1.0.0.dist-info/METADATA
greetings_helloworld2030_2-1.0.0.dist-info/WHEEL
greetings_helloworld2030_2-1.0.0.dist-info/top_level.txt
greetings_helloworld2030_2-1.0.0.dist-info/RECORD
